gunpowder/__init__.py
gunpowder/array.py
gunpowder/array_spec.py
gunpowder/batch.py
gunpowder/batch_request.py
gunpowder/build.py
gunpowder/coordinate.py
gunpowder/freezable.py
gunpowder/graph.py
gunpowder/graph_spec.py
gunpowder/morphology.py
gunpowder/ndarray.py
gunpowder/pipeline.py
gunpowder/producer_pool.py
gunpowder/profiling.py
gunpowder/provider_spec.py
gunpowder/roi.py
gunpowder/version_info.py
gunpowder/contrib/__init__.py
gunpowder/contrib/nodes/__init__.py
gunpowder/contrib/nodes/add_blobs_from_points.py
gunpowder/contrib/nodes/add_boundary_distance_gradients.py
gunpowder/contrib/nodes/add_gt_mask_exclusive_zone.py
gunpowder/contrib/nodes/add_nonsymmetric_affinities.py
gunpowder/contrib/nodes/add_vector_map.py
gunpowder/contrib/nodes/dvid_partner_annotation_source.py
gunpowder/contrib/nodes/hdf5_points_source.py
gunpowder/contrib/nodes/prepare_malis.py
gunpowder/contrib/nodes/zero_out_const_sections.py
gunpowder/ext/__init__.py
gunpowder/ext/zarr_file.py
gunpowder/jax/__init__.py
gunpowder/jax/generic_jax_model.py
gunpowder/jax/nodes/__init__.py
gunpowder/jax/nodes/predict.py
gunpowder/jax/nodes/train.py
gunpowder/nodes/__init__.py
gunpowder/nodes/add_affinities.py
gunpowder/nodes/array_source.py
gunpowder/nodes/astype.py
gunpowder/nodes/balance_labels.py
gunpowder/nodes/batch_filter.py
gunpowder/nodes/batch_provider.py
gunpowder/nodes/crop.py
gunpowder/nodes/csv_points_source.py
gunpowder/nodes/daisy_request_blocks.py
gunpowder/nodes/defect_augment.py
gunpowder/nodes/deform_augment.py
gunpowder/nodes/downsample.py
gunpowder/nodes/dvid_source.py
gunpowder/nodes/elastic_augment.py
gunpowder/nodes/exclude_labels.py
gunpowder/nodes/generic_predict.py
gunpowder/nodes/generic_train.py
gunpowder/nodes/gp_array_source.py
gunpowder/nodes/gp_graph_source.py
gunpowder/nodes/graph_source.py
gunpowder/nodes/grow_boundary.py
gunpowder/nodes/hdf5_source.py
gunpowder/nodes/hdf5_write.py
gunpowder/nodes/hdf5like_source_base.py
gunpowder/nodes/hdf5like_write_base.py
gunpowder-1.4.3.dist-info/licenses/LICENSE
gunpowder-1.4.3.dist-info/METADATA
gunpowder-1.4.3.dist-info/WHEEL
gunpowder-1.4.3.dist-info/top_level.txt
gunpowder-1.4.3.dist-info/RECORD
