Metadata-Version: 2.4
Name: gunpowder
Version: 1.4.3
Summary: A library to facilitate machine learning on large, multi-dimensional images.
Author: Renate Krause, Julia Buhmann, Rodrigo Ceballos Lentini, William Grisaitis, Chris Barnes, Caroline Malin-Mayor, Larissa Heinrich, Philipp Hanslovsky, Sherry Ding, Andrew Champion, Arlo Sheridan, Constantin Pape
Author-email: Jan Funke <funkej@hhmi.org>, William Patton <pattonw@hhmi.org>
License: MIT
Classifier: Programming Language :: Python :: 3
Requires-Python: >=3.9
License-File: LICENSE
Requires-Dist: numpy>=1.24
Requires-Dist: scipy>=1.6
Requires-Dist: h5py>=3.10
Requires-Dist: scikit-image
Requires-Dist: requests
Requires-Dist: augment-nd>=0.1.3
Requires-Dist: tqdm
Requires-Dist: funlib.geometry>=0.3
Requires-Dist: zarr
Requires-Dist: networkx>=3.1
Requires-Dist: funlib.persistence>=0.5
Provides-Extra: dev
Requires-Dist: pytest; extra == "dev"
Requires-Dist: pytest-cov; extra == "dev"
Requires-Dist: flake8; extra == "dev"
Requires-Dist: mypy; extra == "dev"
Requires-Dist: types-requests; extra == "dev"
Requires-Dist: types-tqdm; extra == "dev"
Requires-Dist: black; extra == "dev"
Requires-Dist: ruff; extra == "dev"
Provides-Extra: docs
Requires-Dist: sphinx; extra == "docs"
Requires-Dist: sphinx_rtd_theme; extra == "docs"
Requires-Dist: sphinx_togglebutton; extra == "docs"
Requires-Dist: tomli; extra == "docs"
Requires-Dist: jupyter_sphinx; extra == "docs"
Requires-Dist: ipykernel; extra == "docs"
Requires-Dist: matplotlib; extra == "docs"
Requires-Dist: torch; extra == "docs"
Provides-Extra: pytorch
Requires-Dist: torch; extra == "pytorch"
Provides-Extra: tensorflow
Requires-Dist: tensorflow<2.0; python_version < "3.8" and extra == "tensorflow"
Requires-Dist: protobuf==3.20.*; python_version == "3.7" and extra == "tensorflow"
Provides-Extra: jax
Requires-Dist: jax; extra == "jax"
Requires-Dist: jaxlib; extra == "jax"
Provides-Extra: full
Requires-Dist: torch; extra == "full"
Requires-Dist: tensorflow<2.0; python_version < "3.8" and extra == "full"
Requires-Dist: protobuf==3.20.*; python_version == "3.7" and extra == "full"
Dynamic: license-file
